scep/__init__.py
scep/Client/__init__.py
scep/Client/asn1.py
scep/Client/builders.py
scep/Client/certificate.py
scep/Client/client.py
scep/Client/crl.py
scep/Client/cryptoutils.py
scep/Client/enums.py
scep/Client/envelope.py
scep/Client/message.py
scep/Client/privatekey.py
scep/Client/publickey.py
scep/Client/responses.py
scep/Client/signingrequest.py
scep/Server/__init__.py
scep/_commons/__init__.py
PyScep-0.0.14.dist-info/LICENSE
PyScep-0.0.14.dist-info/METADATA
PyScep-0.0.14.dist-info/WHEEL
PyScep-0.0.14.dist-info/top_level.txt
PyScep-0.0.14.dist-info/RECORD
