Metadata-Version: 2.1
Name: PyScep
Version: 0.0.14
Summary: A Python SCEP client and server
Home-page: https://github.com/bikram990/PyScep
Download-URL: https://github.com/bikram990/PyScep/archive/refs/tags/0.0.14.tar.gz
Author: Bikramjeet Singh
License: MIT
Project-URL: Bug Tracker, https://github.com/bikram990/PyScep/issues
Classifier: Development Status :: 3 - Alpha
Classifier: License :: OSI Approved :: MIT License
Classifier: Operating System :: OS Independent
Classifier: Natural Language :: English
Classifier: Programming Language :: Python :: 3.8
Classifier: Intended Audience :: Developers
Classifier: Intended Audience :: Science/Research
Classifier: Intended Audience :: System Administrators
Classifier: Topic :: Security
Classifier: Topic :: System :: Installation/Setup
Classifier: Topic :: Utilities
Requires-Python: >=2.7
License-File: LICENSE
